<?xml version="1.0" encoding="UTF-8"?>
<Configuration status="ERROR">
	<Appenders>
		<Console name="Console" target="SYSTEM_OUT">
			<PatternLayout pattern="%-5level %c{1}:%M:%L - %msg%n" />
<!--
 -->		
 		</Console>
	</Appenders>
	<Loggers>
    <!-- The Root logger can be controlled by the JVM argument -Dlog.level e.g.
         log.level=INFO
    -->
		<Root level="ERROR">
			<AppenderRef ref="Console" />
		</Root>
    <!-- For deep logging in any package add the leve attribute below
         level="INFO"
    -->
    <Logger name="com.rodini.ballotgen"> 
		<RegexFilter regex="No subclass found for /word/media/hdphoto1.wdp; defaulting to binary" onMatch="DENY" onMismatch="ACCEPT" />
    </Logger>
    <Logger name="com.rodini.ballotgen.common"> 
    </Logger>
    <Logger name="com.rodini.ballotgen.contest"> 
    </Logger>
    <Logger name="com.rodini.ballotgen.endorsement"> 
    </Logger>
    <Logger name="com.rodini.ballotgen.placeholder"> 
    </Logger>
    <Logger name="com.rodini.ballotgen.writein"> 
    </Logger>
	</Loggers>
</Configuration>